pypenny/__init__.py
pypenny/_core.py
pypenny/config.py
pypenny/currency_manager.py
pypenny/encryption_utils.py
pypenny/exceptions.py
pypenny/exchange_cache.py
pypenny/locale_matcher.py
pypenny/money.py
pypenny/py.typed
pypenny-0.1.0.post1.dist-info/METADATA
pypenny-0.1.0.post1.dist-info/WHEEL
pypenny-0.1.0.post1.dist-info/licenses/LICENSE
pypenny-0.1.0.post1.dist-info/RECORD
