Metadata-Version: 2.4
Name: pypenny
Version: 0.1.0.post1
Summary: Production-grade currency conversion with smart error handling, encrypted caching, and fuzzy locale matching
Project-URL: Homepage, https://github.com/alaamer12/robust-currency
Project-URL: Documentation, https://github.com/alaamer12/robust-currency#readme
Project-URL: Repository, https://github.com/alaamer12/robust-currency
Project-URL: Issues, https://github.com/alaamer12/robust-currency/issues
Author-email: Your Name <your.email@example.com>
License: MIT
License-File: LICENSE
Keywords: babel,cache,conversion,currency,encryption,exchange-rates,forex,locale,money
Classifier: Development Status :: 5 - Production/Stable
Classifier: Intended Audience :: Developers
Classifier: License :: OSI Approved :: MIT License
Classifier: Programming Language :: Python :: 3
Classifier: Programming Language :: Python :: 3.8
Classifier: Programming Language :: Python :: 3.9
Classifier: Programming Language :: Python :: 3.10
Classifier: Programming Language :: Python :: 3.11
Classifier: Programming Language :: Python :: 3.12
Classifier: Topic :: Office/Business :: Financial
Classifier: Topic :: Software Development :: Libraries :: Python Modules
Classifier: Typing :: Typed
Requires-Python: >=3.8
Requires-Dist: babel>=2.12.0
Requires-Dist: cryptography>=41.0.0
Requires-Dist: platformdirs>=4.0.0
Requires-Dist: py-moneyed>=3.0
Requires-Dist: pytest>=8.3.5
Requires-Dist: python-levenshtein>=0.21.0
Requires-Dist: requests>=2.31.0
Provides-Extra: dev
Requires-Dist: mypy>=1.5.0; extra == 'dev'
Requires-Dist: pytest-asyncio>=0.21.0; extra == 'dev'
Requires-Dist: pytest-cov>=4.1.0; extra == 'dev'
Requires-Dist: pytest>=7.4.0; extra == 'dev'
Requires-Dist: ruff>=0.1.0; extra == 'dev'
